pyscreenrec/__init__.py
pyscreenrec-0.5.dist-info/LICENSE
pyscreenrec-0.5.dist-info/METADATA
pyscreenrec-0.5.dist-info/WHEEL
pyscreenrec-0.5.dist-info/top_level.txt
pyscreenrec-0.5.dist-info/RECORD
