Metadata-Version: 2.1
Name: pyscreenrec
Version: 0.5
Summary: A small and cross-platform python library for recording screen.
Home-page: https://github.com/shravanasati/pyscreenrec
Author: Shravan Asati
Author-email: dev.shravan@protonmail.com
License: MIT
Keywords: python,screen recording,screen,recording,screenshots
Classifier: Development Status :: 3 - Alpha
Classifier: Intended Audience :: Developers
Classifier: License :: OSI Approved :: MIT License
Classifier: Programming Language :: Python :: 3.6
Classifier: Programming Language :: Python :: 3.7
Classifier: Programming Language :: Python :: 3.8
Classifier: Programming Language :: Python :: 3.9
Classifier: Operating System :: Unix
Classifier: Operating System :: MacOS :: MacOS X
Classifier: Operating System :: Microsoft :: Windows
Classifier: Topic :: Software Development :: Libraries
License-File: LICENSE
Requires-Dist: pyscreeze
Requires-Dist: opencv-python
Requires-Dist: natsort
